datasets/drug.csv
datasets/insta.csv
datasets/sales.csv
datasets/transactions.csv
gdd/__init__.py
gdd/exp2_olap.py
gdd/exp3_dt.py
gdd/exp4_lr.py
gdd/exp5_kmeans.py
gdd/exp6_hcluster.py
gdd/exp7_ap.py
gdd_package-0.1.3.dist-info/LICENSE
gdd_package-0.1.3.dist-info/METADATA
gdd_package-0.1.3.dist-info/WHEEL
gdd_package-0.1.3.dist-info/top_level.txt
gdd_package-0.1.3.dist-info/RECORD
