Metadata-Version: 2.1
Name: gdd-package
Version: 0.1.3
Summary: GDD - A comprehensive data science and machine learning package
Home-page: https://github.com/gdd02/gdd-package
Author: gdd02
Author-email: gdd02@example.com
Project-URL: Bug Reports, https://github.com/gdd02/gdd-package/issues
Project-URL: Source, https://github.com/gdd02/gdd-package
Keywords: data science,machine learning,analytics,clustering,classification
Classifier: Development Status :: 3 - Alpha
Classifier: Intended Audience :: Developers
Classifier: Intended Audience :: Science/Research
Classifier: License :: OSI Approved :: MIT License
Classifier: Programming Language :: Python :: 3
Classifier: Programming Language :: Python :: 3.8
Classifier: Programming Language :: Python :: 3.9
Classifier: Programming Language :: Python :: 3.10
Classifier: Programming Language :: Python :: 3.11
Classifier: Topic :: Scientific/Engineering :: Artificial Intelligence
Classifier: Topic :: Software Development :: Libraries :: Python Modules
Requires-Python: >=3.8
License-File: LICENSE
Requires-Dist: pandas (<2.1.0,>=1.3.0)
Requires-Dist: numpy (<2.0.0,>=1.21.0)
Requires-Dist: matplotlib (>=3.3.0)
Requires-Dist: scikit-learn (>=1.0.0)
Requires-Dist: mlxtend (>=0.19.0)
Requires-Dist: scipy (>=1.7.0)
